package interpreter

// JVM opcode mnemonics (JVMS §6.5). Defined as constants so the dispatch switch
// reads as the spec; values are the opcode bytes. Opcodes catty does not yet
// implement (e.g. invokedynamic, jsr) still have constants here so the default
// case can name them precisely when it panics.
const (
	opNop                = 0x00
	opAconstNull         = 0x01
	opIconstM1           = 0x02
	opIconst0            = 0x03
	opIconst1            = 0x04
	opIconst2            = 0x05
	opIconst3            = 0x06
	opIconst4            = 0x07
	opIconst5            = 0x08
	opLconst0            = 0x09
	opLconst1            = 0x0a
	opFconst0            = 0x0b
	opFconst1            = 0x0c
	opFconst2            = 0x0d
	opDconst0            = 0x0e
	opDconst1            = 0x0f
	opBipush             = 0x10
	opSipush             = 0x11
	opLdc                = 0x12
	opLdcW               = 0x13
	opLdc2W              = 0x14
	opIload              = 0x15
	opLload              = 0x16
	opFload              = 0x17
	opDload              = 0x18
	opAload              = 0x19
	opIload0             = 0x1a
	opIload1             = 0x1b
	opIload2             = 0x1c
	opIload3             = 0x1d
	opLload0             = 0x1e
	opLload1             = 0x1f
	opLload2             = 0x20
	opLload3             = 0x21
	opFload0             = 0x22
	opFload1             = 0x23
	opFload2             = 0x24
	opFload3             = 0x25
	opDload0             = 0x26
	opDload1             = 0x27
	opDload2             = 0x28
	opDload3             = 0x29
	opAload0             = 0x2a
	opAload1             = 0x2b
	opAload2             = 0x2c
	opAload3             = 0x2d
	opIaload             = 0x2e
	opLaload             = 0x2f
	opFaload             = 0x30
	opDaload             = 0x31
	opAaload             = 0x32
	opBaload             = 0x33
	opCaload             = 0x34
	opSaload             = 0x35
	opIstore             = 0x36
	opLstore             = 0x37
	opFstore             = 0x38
	opDstore             = 0x39
	opAstore             = 0x3a
	opIstore0            = 0x3b
	opIstore1            = 0x3c
	opIstore2            = 0x3d
	opIstore3            = 0x3e
	opLstore0            = 0x3f
	opLstore1            = 0x40
	opLstore2            = 0x41
	opLstore3            = 0x42
	opFstore0            = 0x43
	opFstore1            = 0x44
	opFstore2            = 0x45
	opFstore3            = 0x46
	opDstore0            = 0x47
	opDstore1            = 0x48
	opDstore2            = 0x49
	opDstore3            = 0x4a
	opAstore0            = 0x4b
	opAstore1            = 0x4c
	opAstore2            = 0x4d
	opAstore3            = 0x4e
	opIastore            = 0x4f
	opLastore            = 0x50
	opFastore            = 0x51
	opDastore            = 0x52
	opAastore            = 0x53
	opBastore            = 0x54
	opCastore            = 0x55
	opSastore            = 0x56
	opPop                = 0x57
	opPop2               = 0x58
	opDup                = 0x59
	opDupX1              = 0x5a
	opDupX2              = 0x5b
	opDup2               = 0x5c
	opDup2X1             = 0x5d
	opDup2X2             = 0x5e
	opSwap               = 0x5f
	opIadd               = 0x60
	opLadd               = 0x61
	opFadd               = 0x62
	opDadd               = 0x63
	opIsub               = 0x64
	opLsub               = 0x65
	opFsub               = 0x66
	opDsub               = 0x67
	opImul               = 0x68
	opLmul               = 0x69
	opFmul               = 0x6a
	opDmul               = 0x6b
	opIdiv               = 0x6c
	opLdiv               = 0x6d
	opFdiv               = 0x6e
	opDdiv               = 0x6f
	opIrem               = 0x70
	opLrem               = 0x71
	opFrem               = 0x72
	opDrem               = 0x73
	opIneg               = 0x74
	opLneg               = 0x75
	opFneg               = 0x76
	opDneg               = 0x77
	opIshl               = 0x78
	opLshl               = 0x79
	opIshr               = 0x7a
	opLshr               = 0x7b
	opIushr              = 0x7c
	opLushr              = 0x7d
	opIand               = 0x7e
	opLand               = 0x7f
	opIor                = 0x80
	opLor                = 0x81
	opIxor               = 0x82
	opLxor               = 0x83
	opIinc               = 0x84
	opI2l                = 0x85
	opI2f                = 0x86
	opI2d                = 0x87
	opL2i                = 0x88
	opL2f                = 0x89
	opL2d                = 0x8a
	opF2i                = 0x8b
	opF2l                = 0x8c
	opF2d                = 0x8d
	opD2i                = 0x8e
	opD2l                = 0x8f
	opD2f                = 0x90
	opI2b                = 0x91
	opI2c                = 0x92
	opI2s                = 0x93
	opLcmp               = 0x94
	opFcmpl              = 0x95
	opFcmpg              = 0x96
	opDcmpl              = 0x97
	opDcmpg              = 0x98
	opIfeq               = 0x99
	opIfne               = 0x9a
	opIflt               = 0x9b
	opIfge               = 0x9c
	opIfgt               = 0x9d
	opIfle               = 0x9e
	opIfIcmpeq           = 0x9f
	opIfIcmpne           = 0xa0
	opIfIcmplt           = 0xa1
	opIfIcmpge           = 0xa2
	opIfIcmpgt           = 0xa3
	opIfIcmple           = 0xa4
	opIfAcmpeq           = 0xa5
	opIfAcmpne           = 0xa6
	opGoto               = 0xa7
	opTableswitch        = 0xaa
	opLookupswitch       = 0xab
	opIreturn            = 0xac
	opLreturn            = 0xad
	opFreturn            = 0xae
	opDreturn            = 0xaf
	opAreturn            = 0xb0
	opReturn             = 0xb1
	opGetstatic          = 0xb2
	opPutstatic          = 0xb3
	opGetfield           = 0xb4
	opPutfield           = 0xb5
	opInvokevirtual      = 0xb6
	opInvokespecial      = 0xb7
	opInvokestatic       = 0xb8
	opInvokeinterface    = 0xb9
	opInvokedynamic      = 0xba
	opNew                = 0xbb
	opNewarray           = 0xbc
	opAnewarray          = 0xbd
	opArraylength        = 0xbe
	opAthrow             = 0xbf
	opCheckcast          = 0xc0
	opInstanceof         = 0xc1
	opMonitorenter       = 0xc2
	opMonitorexit        = 0xc3
	opWide               = 0xc4
	opMultianewarray     = 0xc5
	opIfnull             = 0xc6
	opIfnonnull          = 0xc7
	opGotoW              = 0xc8
)

// opcodeName is for panic messages in the default case.
var opcodeName = [...]string{
	opInvokedynamic: "invokedynamic",
	opInvokeinterface: "invokeinterface",
	opMultianewarray: "multianewarray",
	opWide: "wide",
}
